demo/apps/__init__.py
demo/apps/user/__init__.py
demo/apps/user/admin.py
demo/apps/user/models.py
demo/apps/user/migrations/0001_initial.py
demo/apps/user/migrations/__init__.py
sms_auth/__init__.py
sms_auth/admin.py
sms_auth/apps.py
sms_auth/conf.py
sms_auth/listeners.py
sms_auth/tasks.py
sms_auth/utils.py
sms_auth/api/__init__.py
sms_auth/api/exceptions.py
sms_auth/api/mixins.py
sms_auth/api/serializers.py
sms_auth/api/urls.py
sms_auth/api/views.py
sms_auth/management/__init__.py
sms_auth/management/commands/__init__.py
sms_auth/management/commands/clear_expired.py
sms_auth/migrations/0001_initial.py
sms_auth/migrations/__init__.py
sms_auth/models/__init__.py
sms_auth/models/sms.py
sms_auth/providers/__init__.py
sms_auth/providers/base.py
sms_auth/providers/megafon/__init__.py
sms_auth/providers/smsaero/__init__.py
sms_auth/providers/smsaero/smsaero.py
sms_auth/providers/twilio/__init__.py
sms_auth/services/__init__.py
sms_auth/services/auth.py
sms_auth/services/clean.py
sms_auth/services/generator.py
django_rest_sms_auth-0.1.22.dist-info/LICENSE.txt
django_rest_sms_auth-0.1.22.dist-info/METADATA
django_rest_sms_auth-0.1.22.dist-info/WHEEL
django_rest_sms_auth-0.1.22.dist-info/top_level.txt
django_rest_sms_auth-0.1.22.dist-info/RECORD
