Metadata-Version: 2.1
Name: django-rest-sms-auth
Version: 0.1.22
Summary: Django users authentication through SMS code
Home-page: https://github.com/a1k89/django-rest-sms-auth
Author: Andrei Koptev
Author-email: akoptev1989@ya.ru
License: MIT
Keywords: django rest auth sms registration rest-framework django-registration sms
Platform: UNKNOWN
Classifier: Framework :: Django
Classifier: Intended Audience :: Developers
Classifier: Intended Audience :: System Administrators
Classifier: Operating System :: OS Independent
Classifier: Topic :: Software Development
Requires-Dist: Django (>=2.0)
Requires-Dist: djangorestframework (>=3.0)
Requires-Dist: phonenumbers
Requires-Dist: django-phonenumber-field
Requires-Dist: celery (>=5.0)
